Workbook
Name Slicer_Category: #N/A
Name Slicer_Region: #N/A
Name Slicer_Segment1: #N/A
Name Slicer_Years__Order_Date: #N/A

Sheet Sales Data
A1: Row ID | B1: Order ID | C1: Order Date | D1: Ship Date | E1: Ship Mode | F1: Customer ID | G1: Customer Name | H1: Segment | I1: Country | J1: City | K1: State | L1: Postal Code | M1: Region | N1: Product ID | O1: Category | P1: Sub-Category | Q1: Product Name | R1: Sales
A2: 1 | B2: CA-2017-152156 | C2: 43047 | D2: 43050 | E2: Second Class | F2: CG-12520 | G2: Claire Gute | H2: Consumer | I2: United States | J2: Henderson | K2: Kentucky | L2: 42420 | M2: South | N2: FUR-BO-10001798 | O2: Furniture | P2: Bookcases | Q2: Bush Somerset Collection Bookcase | R2: 261.96
A3: 2 | B3: CA-2017-152156 | C3: 43047 | D3: 43050 | E3: Second Class | F3: CG-12520 | G3: Claire Gute | H3: Consumer | I3: United States | J3: Henderson | K3: Kentucky | L3: 42420 | M3: South | N3: FUR-CH-10000454 | O3: Furniture | P3: Chairs | Q3: Hon Deluxe Fabric Upholstered Stacking Chairs, Rounded Back | R3: 731.94
A4: 3 | B4: CA-2017-138688 | C4: 42898 | D4: 42902 | E4: Second Class | F4: DV-13045 | G4: Darrin Van Huff | H4: Corporate | I4: United States | J4: Los Angeles | K4: California | L4: 90036 | M4: West | N4: OFF-LA-10000240 | O4: Office Supplies | P4: Labels | Q4: Self-Adhesive Address Labels for Typewriters by Universal | R4: 14.62
A5: 4 | B5: US-2016-108966 | C5: 42654 | D5: 42661 | E5: Standard Class | F5: SO-20335 | G5: Sean O'Donnell | H5: Consumer | I5: United States | J5: Fort Lauderdale | K5: Florida | L5: 33311 | M5: South | N5: FUR-TA-10000577 | O5: Furniture | P5: Tables | Q5: Bretford CR4500 Series Slim Rectangular Table | R5: 957.5775
A6: 5 | B6: US-2016-108966 | C6: 42654 | D6: 42661 | E6: Standard Class | F6: SO-20335 | G6: Sean O'Donnell | H6: Consumer | I6: United States | J6: Fort Lauderdale | K6: Florida | L6: 33311 | M6: South | N6: OFF-ST-10000760 | O6: Office Supplies | P6: Storage | Q6: Eldon Fold 'N Roll Cart System | R6: 22.368
A7: 6 | B7: CA-2015-115812 | C7: 42164 | D7: 42169 | E7: Standard Class | F7: BH-11710 | G7: Brosina Hoffman | H7: Consumer | I7: United States | J7: Los Angeles | K7: California | L7: 90032 | M7: West | N7: FUR-FU-10001487 | O7: Furniture | P7: Furnishings | Q7: Eldon Expressions Wood and Plastic Desk Accessories, Cherry Wood | R7: 48.86
A8: 7 | B8: CA-2015-115812 | C8: 42164 | D8: 42169 | E8: Standard Class | F8: BH-11710 | G8: Brosina Hoffman | H8: Consumer | I8: United States | J8: Los Angeles | K8: California | L8: 90032 | M8: West | N8: OFF-AR-10002833 | O8: Office Supplies | P8: Art | Q8: Newell 322 | R8: 7.28
A9: 8 | B9: CA-2015-115812 | C9: 42164 | D9: 42169 | E9: Standard Class | F9: BH-11710 | G9: Brosina Hoffman | H9: Consumer | I9: United States | J9: Los Angeles | K9: California | L9: 90032 | M9: West | N9: TEC-PH-10002275 | O9: Technology | P9: Phones | Q9: Mitel 5320 IP Phone VoIP phone | R9: 907.152
A10: 9 | B10: CA-2015-115812 | C10: 42164 | D10: 42169 | E10: Standard Class | F10: BH-11710 | G10: Brosina Hoffman | H10: Consumer | I10: United States | J10: Los Angeles | K10: California | L10: 90032 | M10: West | N10: OFF-BI-10003910 | O10: Office Supplies | P10: Binders | Q10: DXL Angle-View Binders with Locking Rings by Samsill | R10: 18.504
A11: 10 | B11: CA-2015-115812 | C11: 42164 | D11: 42169 | E11: Standard Class | F11: BH-11710 | G11: Brosina Hoffman | H11: Consumer | I11: United States | J11: Los Angeles | K11: California | L11: 90032 | M11: West | N11: OFF-AP-10002892 | O11: Office Supplies | P11: Appliances | Q11: Belkin F5C206VTEL 6 Outlet Surge | R11: 114.9
A12: 11 | B12: CA-2015-115812 | C12: 42164 | D12: 42169 | E12: Standard Class | F12: BH-11710 | G12: Brosina Hoffman | H12: Consumer | I12: United States | J12: Los Angeles | K12: California | L12: 90032 | M12: West | N12: FUR-TA-10001539 | O12: Furniture | P12: Tables | Q12: Chromcraft Rectangular Conference Tables | R12: 1706.184
A13: 12 | B13: CA-2015-115812 | C13: 42164 | D13: 42169 | E13: Standard Class | F13: BH-11710 | G13: Brosina Hoffman | H13: Consumer | I13: United States | J13: Los Angeles | K13: California | L13: 90032 | M13: West | N13: TEC-PH-10002033 | O13: Technology | P13: Phones | Q13: Konftel 250 Conference¬†phone¬†- Charcoal black | R13: 911.424
... A2235: 2234 | B2235: CA-2016-123232 | C2235: 42718 | D2235: 42720 | E2235: Second Class | F2235: DJ-13630 | G2235: Doug Jacobs | H2235: Consumer | I2235: United States | J2235: Portland | K2235: Oregon | L2235: 97206 | M2235: West | N2235: TEC-PH-10001051 | O2235: Technology | P2235: Phones | Q2235: HTC One | R2235: 319.968
A2236: 2235 | B2236: CA-2018-104066 | C2236: 43439 | D2236: 43444 | E2236: Standard Class | F2236: QJ-19255 | G2236: Quincy Jones | H2236: Corporate | I2236: United States | J2236: Burlington | K2236: Vermont | M2236: East | N2236: TEC-AC-10001013 | O2236: Technology | P2236: Accessories | Q2236: Logitech ClearChat Comfort/USB Headset H390 | R2236: 205.03
A2237: 2236 | B2237: CA-2016-145849 | C2237: 42628 | D2237: 42630 | E2237: Second Class | F2237: CT-11995 | G2237: Carol Triggs | H2237: Consumer | I2237: United States | J2237: Indianapolis | K2237: Indiana | L2237: 46203 | M2237: Central | N2237: OFF-ST-10000025 | O2237: Office Supplies | P2237: Storage | Q2237: Fellowes Stor/Drawer Steel Plus Storage Drawers | R2237: 190.86
A2238: 2237 | B2238: CA-2016-145849 | C2238: 42628 | D2238: 42630 | E2238: Second Class | F2238: CT-11995 | G2238: Carol Triggs | H2238: Consumer | I2238: United States | J2238: Indianapolis | K2238: Indiana | L2238: 46203 | M2238: Central | N2238: OFF-AR-10000817 | O2238: Office Supplies | P2238: Art | Q2238: Manco Dry-Lighter Erasable Highlighter | R2238: 24.32
A2239: 2238 | B2239: CA-2017-122322 | C2239: 42931 | D2239: 42937 | E2239: Standard Class | F2239: RH-19510 | G2239: Rick Huthwaite | H2239: Home Office | I2239: United States | J2239: Provo | K2239: Utah | L2239: 84604 | M2239: West | N2239: OFF-SU-10000952 | O2239: Office Supplies | P2239: Supplies | Q2239: Fiskars Home & Office Scissors | R2239: 44.4
A2240: 2239 | B2240: CA-2018-166849 | C2240: 43210 | D2240: 43216 | E2240: Standard Class | F2240: SJ-20125 | G2240: Sanjit Jacobs | H2240: Home Office | I2240: United States | J2240: Chicago | K2240: Illinois | L2240: 60610 | M2240: Central | N2240: FUR-FU-10004597 | O2240: Furniture | P2240: Furnishings | Q2240: Eldon Cleatmat Chair Mats for Medium Pile Carpets | R2240: 44.4
A2241: 2240 | B2241: CA-2017-146633 | C2241: 43054 | D2241: 43056 | E2241: Second Class | F2241: TG-21310 | G2241: Toby Gnade | H2241: Consumer | I2241: United States | J2241: Los Angeles | K2241: California | L2241: 90049 | M2241: West | N2241: OFF-BI-10003527 | O2241: Office Supplies | P2241: Binders | Q2241: Fellowes PB500 Electric Punch Plastic Comb Binding Machine with Manual Bind | R2241: 1016.792
A2242: 2241 | B2242: CA-2017-146633 | C2242: 43054 | D2242: 43056 | E2242: Second Class | F2242: TG-21310 | G2242: Toby Gnade | H2242: Consumer | I2242: United States | J2242: Los Angeles | K2242: California | L2242: 90049 | M2242: West | N2242: OFF-BI-10002982 | O2242: Office Supplies | P2242: Binders | Q2242: Avery Self-Adhesive Photo Pockets for Polaroid Photos | R2242: 38.136
A2243: 2242 | B2243: US-2017-126893 | C2243: 43065 | D2243: 43070 | E2243: Standard Class | F2243: CT-11995 | G2243: Carol Triggs | H2243: Consumer | I2243: United States | J2243: Philadelphia | K2243: Pennsylvania | L2243: 19134 | M2243: East | N2243: TEC-PH-10004165 | O2243: Technology | P2243: Phones | Q2243: Mitel MiVoice 5330e IP Phone | R2243: 494.982
A2244: 2243 | B2244: CA-2018-103380 | C2244: 43425 | D2244: 43429 | E2244: Standard Class | F2244: BF-11005 | G2244: Barry Franz | H2244: Home Office | I2244: United States | J2244: Pasadena | K2244: California | L2244: 91104 | M2244: West | N2244: OFF-ST-10003442 | O2244: Office Supplies | P2244: Storage | Q2244: Eldon Portable Mobile Manager | R2244: 56.56
A2245: 2244 | B2245: CA-2018-103380 | C2245: 43425 | D2245: 43429 | E2245: Standard Class | F2245: BF-11005 | G2245: Barry Franz | H2245: Home Office | I2245: United States | J2245: Pasadena | K2245: California | L2245: 91104 | M2245: West | N2245: OFF-AR-10003856 | O2245: Office Supplies | P2245: Art | Q2245: Newell 344 | R2245: 5.56
A2246: 2245 | B2246: CA-2018-103380 | C2246: 43425 | D2246: 43429 | E2246: Standard Class | F2246: BF-11005 | G2246: Barry Franz | H2246: Home Office | I2246: United States | J2246: Pasadena | K2246: California | L2246: 91104 | M2246: West | N2246: OFF-FA-10004248 | O2246: Office Supplies | P2246: Fasteners | Q2246: Advantus T-Pin Paper Clips | R2246: 9.02
A2247: 2246 | B2247: CA-2018-103380 | C2247: 43425 | D2247: 43429 | E2247: Standard Class | F2247: BF-11005 | G2247: Barry Franz | H2247: Home Office | I2247: United States | J2247: Pasadena | K2247: California | L2247: 91104 | M2247: West | N2247: OFF-AP-10001492 | O2247: Office Supplies | P2247: Appliances | Q2247: Acco Six-Outlet Power Strip, 4' Cord Length | R2247: 8.62
A2248: 2247 | B2248: CA-2018-103380 | C2248: 43425 | D2248: 43429 | E2248: Standard Class | F2248: BF-11005 | G2248: Barry Franz | H2248: Home Office | I2248: United States | J2248: Pasadena | K2248: California | L2248: 91104 | M2248: West | N2248: TEC-PH-10004165 | O2248: Technology | P2248: Phones | Q2248: Mitel MiVoice 5330e IP Phone | R2248: 659.976
... A5275: 5274 | B5275: US-2017-158309 | C5275: 43065 | D5275: 43068 | E5275: First Class | F5275: PA-19060 | G5275: Pete Armstrong | H5275: Home Office | I5275: United States | J5275: Miami | K5275: Florida | L5275: 33142 | M5275: South | N5275: OFF-BI-10000145 | O5275: Office Supplies | P5275: Binders | Q5275: Zipper Ring Binder Pockets | R5275: 3.744
A5276: 5275 | B5276: CA-2016-162887 | C5276: 42681 | D5276: 42683 | E5276: Second Class | F5276: SV-20785 | G5276: Stewart Visinsky | H5276: Consumer | I5276: United States | J5276: Burlington | K5276: Vermont | M5276: East | N5276: FUR-CH-10000595 | O5276: Furniture | P5276: Chairs | Q5276: Safco Contoured Stacking Chairs | R5276: 715.2
A5277: 5276 | B5277: CA-2018-147333 | C5277: 43448 | D5277: 43454 | E5277: Standard Class | F5277: KL-16555 | G5277: Kelly Lampkin | H5277: Corporate | I5277: United States | J5277: Fayetteville | K5277: Arkansas | L5277: 72701 | M5277: South | N5277: TEC-AC-10004469 | O5277: Technology | P5277: Accessories | Q5277: Microsoft Sculpt Comfort Mouse | R5277: 159.8
A5278: 5277 | B5278: CA-2018-147333 | C5278: 43448 | D5278: 43454 | E5278: Standard Class | F5278: KL-16555 | G5278: Kelly Lampkin | H5278: Corporate | I5278: United States | J5278: Fayetteville | K5278: Arkansas | L5278: 72701 | M5278: South | N5278: TEC-AC-10003038 | O5278: Technology | P5278: Accessories | Q5278: Kingston Digital DataTraveler 16GB USB 2.0 | R5278: 44.75
A5279: 5278 | B5279: CA-2015-113859 | C5279: 42260 | D5279: 42264 | E5279: Standard Class | F5279: BC-11125 | G5279: Becky Castell | H5279: Home Office | I5279: United States | J5279: Odessa | K5279: Texas | L5279: 79762 | M5279: Central | N5279: FUR-CH-10004698 | O5279: Furniture | P5279: Chairs | Q5279: Padded Folding Chairs, Black, 4/Carton | R5279: 340.116
A5280: 5279 | B5280: CA-2015-159681 | C5280: 42345 | D5280: 42351 | E5280: Standard Class | F5280: PO-18850 | G5280: Patrick O'Brill | H5280: Consumer | I5280: United States | J5280: Virginia Beach | K5280: Virginia | L5280: 23464 | M5280: South | N5280: OFF-PA-10003641 | O5280: Office Supplies | P5280: Paper | Q5280: Xerox 1909 | R5280: 105.52
A5281: 5280 | B5281: US-2018-104094 | C5281: 43350 | D5281: 43354 | E5281: Standard Class | F5281: AG-10675 | G5281: Anna Gayman | H5281: Consumer | I5281: United States | J5281: Milwaukee | K5281: Wisconsin | L5281: 53209 | M5281: Central | N5281: TEC-AC-10002134 | O5281: Technology | P5281: Accessories | Q5281: Rosewill 107 Normal Keys USB Wired Standard Keyboard | R5281: 13.48
A5282: 5281 | B5282: CA-2018-152709 | C5282: 43380 | D5282: 43385 | E5282: Standard Class | F5282: DB-13210 | G5282: Dean Braden | H5282: Consumer | I5282: United States | J5282: Detroit | K5282: Michigan | L5282: 48234 | M5282: Central | N5282: OFF-ST-10001837 | O5282: Office Supplies | P5282: Storage | Q5282: SAFCO Mobile Desk Side File, Wire Frame | R5282: 85.52
A5283: 5282 | B5283: CA-2016-105158 | C5283: 42618 | D5283: 42623 | E5283: Standard Class | F5283: SP-20860 | G5283: Sung Pak | H5283: Corporate | I5283: United States | J5283: Rochester | K5283: Minnesota | L5283: 55901 | M5283: Central | N5283: FUR-FU-10001706 | O5283: Furniture | P5283: Furnishings | Q5283: Longer-Life Soft White Bulbs | R5283: 6.16
A5284: 5283 | B5284: CA-2016-105158 | C5284: 42618 | D5284: 42623 | E5284: Standard Class | F5284: SP-20860 | G5284: Sung Pak | H5284: Corporate | I5284: United States | J5284: Rochester | K5284: Minnesota | L5284: 55901 | M5284: Central | N5284: OFF-PA-10001970 | O5284: Office Supplies | P5284: Paper | Q5284: Xerox 1881 | R5284: 36.84
A5285: 5284 | B5285: CA-2015-133424 | C5285: 42093 | D5285: 42098 | E5285: Standard Class | F5285: Dl-13600 | G5285: Dorris liebe | H5285: Corporate | I5285: United States | J5285: Seattle | K5285: Washington | L5285: 98105 | M5285: West | N5285: OFF-ST-10002957 | O5285: Office Supplies | P5285: Storage | Q5285: Sterilite Show Offs Storage Containers | R5285: 15.84
A5286: 5285 | B5286: CA-2015-133424 | C5286: 42093 | D5286: 42098 | E5286: Standard Class | F5286: Dl-13600 | G5286: Dorris liebe | H5286: Corporate | I5286: United States | J5286: Seattle | K5286: Washington | L5286: 98105 | M5286: West | N5286: OFF-LA-10002312 | O5286: Office Supplies | P5286: Labels | Q5286: Avery 490 | R5286: 44.4
A5287: 5286 | B5287: CA-2018-105991 | C5287: 43225 | D5287: 43226 | E5287: First Class | F5287: LH-17020 | G5287: Lisa Hazard | H5287: Consumer | I5287: United States | J5287: Louisville | K5287: Colorado | L5287: 80027 | M5287: West | N5287: OFF-EN-10002600 | O5287: Office Supplies | P5287: Envelopes | Q5287: Redi-Strip #10 Envelopes, 4 1/8 x 9 1/2 | R5287: 21.24
A5288: 5287 | B5288: CA-2018-105991 | C5288: 43225 | D5288: 43226 | E5288: First Class | F5288: LH-17020 | G5288: Lisa Hazard | H5288: Consumer | I5288: United States | J5288: Louisville | K5288: Colorado | L5288: 80027 | M5288: West | N5288: OFF-BI-10003274 | O5288: Office Supplies | P5288: Binders | Q5288: Avery Durable Slant Ring Binders, No Labels | R5288: 9.552
... A8799: 8798 | B8799: CA-2017-106397 | C8799: 42923 | D8799: 42929 | E8799: Standard Class | F8799: MJ-17740 | G8799: Max Jones | H8799: Consumer | I8799: United States | J8799: Orem | K8799: Utah | L8799: 84057 | M8799: West | N8799: OFF-AR-10004602 | O8799: Office Supplies | P8799: Art | Q8799: Boston KS Multi-Size Manual Pencil Sharpener | R8799: 45.98
A8800: 8799 | B8800: US-2017-150140 | C8800: 42831 | D8800: 42835 | E8800: Standard Class | F8800: VM-21685 | G8800: Valerie Mitchum | H8800: Home Office | I8800: United States | J8800: Burlington | K8800: Vermont | M8800: East | N8800: TEC-PH-10002555 | O8800: Technology | P8800: Phones | Q8800: Nortel Meridian M5316 Digital phone | R8800: 1294.75
A8801: 8800 | B8801: CA-2015-116666 | C8801: 42132 | D8801: 42134 | E8801: First Class | F8801: KT-16480 | G8801: Kean Thornton | H8801: Consumer | I8801: United States | J8801: Philadelphia | K8801: Pennsylvania | L8801: 19134 | M8801: East | N8801: TEC-CO-10001449 | O8801: Technology | P8801: Copiers | Q8801: Hewlett Packard LaserJet 3310 Copier | R8801: 1799.97
A8802: 8801 | B8802: CA-2018-148992 | C8802: 43427 | D8802: 43431 | E8802: Standard Class | F8802: CS-12250 | G8802: Chris Selesnick | H8802: Corporate | I8802: United States | J8802: Chicago | K8802: Illinois | L8802: 60623 | M8802: Central | N8802: OFF-PA-10004285 | O8802: Office Supplies | P8802: Paper | Q8802: Xerox 1959 | R8802: 10.688
A8803: 8802 | B8803: CA-2017-140935 | C8803: 43049 | D8803: 43051 | E8803: First Class | F8803: AB-10015 | G8803: Aaron Bergman | H8803: Consumer | I8803: United States | J8803: Oklahoma City | K8803: Oklahoma | L8803: 73120 | M8803: Central | N8803: TEC-PH-10000562 | O8803: Technology | P8803: Phones | Q8803: Samsung Convoy 3 | R8803: 221.98
A8804: 8803 | B8804: CA-2017-140935 | C8804: 43049 | D8804: 43051 | E8804: First Class | F8804: AB-10015 | G8804: Aaron Bergman | H8804: Consumer | I8804: United States | J8804: Oklahoma City | K8804: Oklahoma | L8804: 73120 | M8804: Central | N8804: FUR-BO-10003966 | O8804: Furniture | P8804: Bookcases | Q8804: Sauder Facets Collection Library, Sky Alder Finish | R8804: 341.96
A8805: 8804 | B8805: CA-2015-157644 | C8805: 42369 | D8805: 42370 | E8805: First Class | F8805: AH-10030 | G8805: Aaron Hawkins | H8805: Corporate | I8805: United States | J8805: New York City | K8805: New York | L8805: 10035 | M8805: East | N8805: TEC-AC-10003614 | O8805: Technology | P8805: Accessories | Q8805: Verbatim 25 GB 6x Blu-ray Single Layer Recordable Disc, 10/Pack | R8805: 34.77
A8806: 8805 | B8806: CA-2015-157644 | C8806: 42369 | D8806: 42370 | E8806: First Class | F8806: AH-10030 | G8806: Aaron Hawkins | H8806: Corporate | I8806: United States | J8806: New York City | K8806: New York | L8806: 10035 | M8806: East | N8806: OFF-LA-10003148 | O8806: Office Supplies | P8806: Labels | Q8806: Avery 51 | R8806: 18.9
A8807: 8806 | B8807: US-2018-100398 | C8807: 43331 | D8807: 43335 | E8807: Standard Class | F8807: DO-13435 | G8807: Denny Ordway | H8807: Consumer | I8807: United States | J8807: Salt Lake City | K8807: Utah | L8807: 84106 | M8807: West | N8807: OFF-BI-10002133 | O8807: Office Supplies | P8807: Binders | Q8807: Wilson Jones Elliptical Ring 3 1/2" Capacity Binders, 800 sheets | R8807: 102.72
A8808: 8807 | B8808: CA-2017-113082 | C8808: 42990 | D8808: 42994 | E8808: Standard Class | F8808: MC-17590 | G8808: Matt Collister | H8808: Corporate | I8808: United States | J8808: Utica | K8808: New York | L8808: 13501 | M8808: East | N8808: FUR-FU-10002813 | O8808: Furniture | P8808: Furnishings | Q8808: DAX Contemporary Wood Frame with Silver Metal Mat, Desktop, 11 x 14 Size | R8808: 40.48
A8809: 8808 | B8809: US-2018-110646 | C8809: 43399 | D8809: 43404 | E8809: Standard Class | F8809: JF-15190 | G8809: Jamie Frazer | H8809: Consumer | I8809: United States | J8809: Philadelphia | K8809: Pennsylvania | L8809: 19134 | M8809: East | N8809: OFF-BI-10004330 | O8809: Office Supplies | P8809: Binders | Q8809: GBC Velobind Prepunched Cover Sets, Regency Series | R8809: 33.282
A8810: 8809 | B8810: US-2018-110646 | C8810: 43399 | D8810: 43404 | E8810: Standard Class | F8810: JF-15190 | G8810: Jamie Frazer | H8810: Consumer | I8810: United States | J8810: Philadelphia | K8810: Pennsylvania | L8810: 19134 | M8810: East | N8810: TEC-PH-10002807 | O8810: Technology | P8810: Phones | Q8810: Motorla HX550 Universal Bluetooth Headset | R8810: 118.65
A8811: 8810 | B8811: US-2018-110646 | C8811: 43399 | D8811: 43404 | E8811: Standard Class | F8811: JF-15190 | G8811: Jamie Frazer | H8811: Consumer | I8811: United States | J8811: Philadelphia | K8811: Pennsylvania | L8811: 19134 | M8811: East | N8811: OFF-LA-10001404 | O8811: Office Supplies | P8811: Labels | Q8811: Avery 517 | R8811: 14.76
A8812: 8811 | B8812: CA-2018-120614 | C8812: 43250 | D8812: 43255 | E8812: Standard Class | F8812: SM-20950 | G8812: Suzanne McNair | H8812: Corporate | I8812: United States | J8812: Los Angeles | K8812: California | L8812: 90004 | M8812: West | N8812: OFF-PA-10004911 | O8812: Office Supplies | P8812: Paper | Q8812: Rediform S.O.S. 1-Up Phone Message Bk, 4-1/4x3-1/16 Bk, 1 Form/Pg, 40 Messages/Bk, 3/Pk | R8812: 37.52
... A9147: 9146 | B9147: CA-2016-126970 | C9147: 42633 | D9147: 42637 | E9147: Standard Class | F9147: TP-21130 | G9147: Theone Pippenger | H9147: Consumer | I9147: United States | J9147: Naperville | K9147: Illinois | L9147: 60540 | M9147: Central | N9147: OFF-BI-10000138 | O9147: Office Supplies | P9147: Binders | Q9147: Acco Translucent Poly Ring Binders | R9147: 2.808
A9148: 9147 | B9148: US-2017-165505 | C9148: 42758 | D9148: 42762 | E9148: Standard Class | F9148: CB-12535 | G9148: Claudia Bergmann | H9148: Corporate | I9148: United States | J9148: Burlington | K9148: Vermont | M9148: East | N9148: TEC-AC-10002926 | O9148: Technology | P9148: Accessories | Q9148: Logitech Wireless Marathon Mouse M705 | R9148: 99.98
A9149: 9148 | B9149: US-2017-165505 | C9149: 42758 | D9149: 42762 | E9149: Standard Class | F9149: CB-12535 | G9149: Claudia Bergmann | H9149: Corporate | I9149: United States | J9149: Burlington | K9149: Vermont | M9149: East | N9149: OFF-AR-10003477 | O9149: Office Supplies | P9149: Art | Q9149: 4009 Highlighters | R9149: 8.04
A9150: 9149 | B9150: US-2017-165505 | C9150: 42758 | D9150: 42762 | E9150: Standard Class | F9150: CB-12535 | G9150: Claudia Bergmann | H9150: Corporate | I9150: United States | J9150: Burlington | K9150: Vermont | M9150: East | N9150: OFF-ST-10001526 | O9150: Office Supplies | P9150: Storage | Q9150: Iceberg Mobile Mega Data/Printer Cart | R9150: 1564.29
A9151: 9150 | B9151: US-2015-157070 | C9151: 42156 | D9151: 42161 | E9151: Standard Class | F9151: QJ-19255 | G9151: Quincy Jones | H9151: Corporate | I9151: United States | J9151: Detroit | K9151: Michigan | L9151: 48234 | M9151: Central | N9151: OFF-BI-10001765 | O9151: Office Supplies | P9151: Binders | Q9151: Wilson Jones Heavy-Duty Casebound Ring Binders with Metal Hinges | R9151: 138.56
A9152: 9151 | B9152: US-2015-157070 | C9152: 42156 | D9152: 42161 | E9152: Standard Class | F9152: QJ-19255 | G9152: Quincy Jones | H9152: Corporate | I9152: United States | J9152: Detroit | K9152: Michigan | L9152: 48234 | M9152: Central | N9152: OFF-AP-10004859 | O9152: Office Supplies | P9152: Appliances | Q9152: Acco 6 Outlet Guardian Premium Surge Suppressor | R9152: 65.52
A9153: 9152 | B9153: US-2016-106873 | C9153: 42637 | D9153: 42642 | E9153: Second Class | F9153: KM-16720 | G9153: Kunst Miller | H9153: Consumer | I9153: United States | J9153: Avondale | K9153: Arizona | L9153: 85323 | M9153: West | N9153: OFF-AR-10003179 | O9153: Office Supplies | P9153: Art | Q9153: Dixon Ticonderoga Core-Lock Colored Pencils | R9153: 14.576
A9154: 9153 | B9154: US-2016-106873 | C9154: 42637 | D9154: 42642 | E9154: Second Class | F9154: KM-16720 | G9154: Kunst Miller | H9154: Consumer | I9154: United States | J9154: Avondale | K9154: Arizona | L9154: 85323 | M9154: West | N9154: TEC-AC-10002345 | O9154: Technology | P9154: Accessories | Q9154: HP Standard 104 key PS/2 Keyboard | R9154: 23.2
A9155: 9154 | B9155: US-2016-106873 | C9155: 42637 | D9155: 42642 | E9155: Second Class | F9155: KM-16720 | G9155: Kunst Miller | H9155: Consumer | I9155: United States | J9155: Avondale | K9155: Arizona | L9155: 85323 | M9155: West | N9155: OFF-AR-10001246 | O9155: Office Supplies | P9155: Art | Q9155: Newell 317 | R9155: 16.464
A9156: 9155 | B9156: CA-2017-132990 | C9156: 42948 | D9156: 42950 | E9156: Second Class | F9156: KM-16660 | G9156: Khloe Miller | H9156: Consumer | I9156: United States | J9156: Philadelphia | K9156: Pennsylvania | L9156: 19140 | M9156: East | N9156: FUR-FU-10004864 | O9156: Furniture | P9156: Furnishings | Q9156: Eldon 500 Class Desk Accessories | R9156: 19.312
A9157: 9156 | B9157: CA-2015-102645 | C9157: 42027 | D9157: 42032 | E9157: Standard Class | F9157: IM-15055 | G9157: Ionia McGrath | H9157: Consumer | I9157: United States | J9157: Las Vegas | K9157: Nevada | L9157: 89115 | M9157: West | N9157: OFF-PA-10001804 | O9157: Office Supplies | P9157: Paper | Q9157: Xerox 195 | R9157: 40.08
A9158: 9157 | B9158: CA-2015-134215 | C9158: 42220 | D9158: 42224 | E9158: Standard Class | F9158: ML-17395 | G9158: Marina Lichtenstein | H9158: Corporate | I9158: United States | J9158: Bangor | K9158: Maine | L9158: 4401 | M9158: East | N9158: OFF-AP-10001271 | O9158: Office Supplies | P9158: Appliances | Q9158: Eureka The Boss Cordless Rechargeable Stick Vac | R9158: 101.96
A9159: 9158 | B9159: CA-2015-134215 | C9159: 42220 | D9159: 42224 | E9159: Standard Class | F9159: ML-17395 | G9159: Marina Lichtenstein | H9159: Corporate | I9159: United States | J9159: Bangor | K9159: Maine | L9159: 4401 | M9159: East | N9159: OFF-PA-10004353 | O9159: Office Supplies | P9159: Paper | Q9159: Southworth 25% Cotton Premium Laser Paper and Envelopes | R9159: 259.74
A9160: 9159 | B9160: CA-2015-134215 | C9160: 42220 | D9160: 42224 | E9160: Standard Class | F9160: ML-17395 | G9160: Marina Lichtenstein | H9160: Corporate | I9160: United States | J9160: Bangor | K9160: Maine | L9160: 4401 | M9160: East | N9160: TEC-AC-10002473 | O9160: Technology | P9160: Accessories | Q9160: Maxell 4.7GB DVD-R | R9160: 255.42
A9161: 9160 | B9161: CA-2017-118934 | C9161: 42956 | D9161: 42961 | E9161: Standard Class | F9161: GH-14410 | G9161: Gary Hansen | H9161: Home Office | I9161: United States | J9161: Hendersonville | K9161: Tennessee | L9161: 37075 | M9161: South | N9161: OFF-BI-10003314 | O9161: Office Supplies | P9161: Binders | Q9161: Tuff Stuff Recycled Round Ring Binders | R9161: 4.338
A9162: 9161 | B9162: CA-2017-118934 | C9162: 42956 | D9162: 42961 | E9162: Standard Class | F9162: GH-14410 | G9162: Gary Hansen | H9162: Home Office | I9162: United States | J9162: Hendersonville | K9162: Tennessee | L9162: 37075 | M9162: South | N9162: OFF-BI-10004465 | O9162: Office Supplies | P9162: Binders | Q9162: Avery Durable Slant Ring Binders | R9162: 11.88
... A9387: 9386 | B9387: CA-2018-163097 | C9387: 43339 | D9387: 43343 | E9387: Standard Class | F9387: SF-20200 | G9387: Sarah Foster | H9387: Consumer | I9387: United States | J9387: Mesa | K9387: Arizona | L9387: 85204 | M9387: West | N9387: FUR-FU-10004973 | O9387: Furniture | P9387: Furnishings | Q9387: Flat Face Poster Frame | R9387: 120.576
A9388: 9387 | B9388: US-2018-127292 | C9388: 43119 | D9388: 43123 | E9388: Standard Class | F9388: RM-19375 | G9388: Raymond Messe | H9388: Consumer | I9388: United States | J9388: Burlington | K9388: Vermont | M9388: East | N9388: OFF-PA-10000157 | O9388: Office Supplies | P9388: Paper | Q9388: Xerox 191 | R9388: 79.92
A9389: 9388 | B9389: US-2018-127292 | C9389: 43119 | D9389: 43123 | E9389: Standard Class | F9389: RM-19375 | G9389: Raymond Messe | H9389: Consumer | I9389: United States | J9389: Burlington | K9389: Vermont | M9389: East | N9389: OFF-PA-10001970 | O9389: Office Supplies | P9389: Paper | Q9389: Xerox 1881 | R9389: 12.28
A9390: 9389 | B9390: US-2018-127292 | C9390: 43119 | D9390: 43123 | E9390: Standard Class | F9390: RM-19375 | G9390: Raymond Messe | H9390: Consumer | I9390: United States | J9390: Burlington | K9390: Vermont | M9390: East | N9390: OFF-AP-10000828 | O9390: Office Supplies | P9390: Appliances | Q9390: Avanti 4.4 Cu. Ft. Refrigerator | R9390: 542.94
A9391: 9390 | B9391: US-2018-127292 | C9391: 43119 | D9391: 43123 | E9391: Standard Class | F9391: RM-19375 | G9391: Raymond Messe | H9391: Consumer | I9391: United States | J9391: Burlington | K9391: Vermont | M9391: East | N9391: OFF-EN-10001509 | O9391: Office Supplies | P9391: Envelopes | Q9391: Poly String Tie Envelopes | R9391: 2.04
A9392: 9391 | B9392: CA-2016-163734 | C9392: 42540 | D9392: 42545 | E9392: Standard Class | F9392: KM-16375 | G9392: Katherine Murray | H9392: Home Office | I9392: United States | J9392: Houston | K9392: Texas | L9392: 77070 | M9392: Central | N9392: OFF-ST-10003692 | O9392: Office Supplies | P9392: Storage | Q9392: Recycled Steel Personal File for Hanging File Folders | R9392: 228.92
A9393: 9392 | B9393: CA-2018-162474 | C9393: 43172 | D9393: 43175 | E9393: First Class | F9393: FH-14275 | G9393: Frank Hawley | H9393: Corporate | I9393: United States | J9393: Aurora | K9393: Illinois | L9393: 60505 | M9393: Central | N9393: TEC-PH-10004700 | O9393: Technology | P9393: Phones | Q9393: PowerGen Dual USB Car Charger | R9393: 7.992
A9394: 9393 | B9394: CA-2016-130848 | C9394: 42668 | D9394: 42668 | E9394: Same Day | F9394: DG-13300 | G9394: Deirdre Greer | H9394: Corporate | I9394: United States | J9394: Denver | K9394: Colorado | L9394: 80219 | M9394: West | N9394: FUR-CH-10000422 | O9394: Furniture | P9394: Chairs | Q9394: Global Highback Leather Tilter in Burgundy | R9394: 582.336
A9395: 9394 | B9395: CA-2015-125997 | C9395: 42267 | D9395: 42270 | E9395: First Class | F9395: MW-18220 | G9395: Mitch Webber | H9395: Consumer | I9395: United States | J9395: New York City | K9395: New York | L9395: 10011 | M9395: East | N9395: TEC-PH-10003484 | O9395: Technology | P9395: Phones | Q9395: Ooma Telo VoIP Home Phone System | R9395: 629.95
A9396: 9395 | B9396: CA-2015-125997 | C9396: 42267 | D9396: 42270 | E9396: First Class | F9396: MW-18220 | G9396: Mitch Webber | H9396: Consumer | I9396: United States | J9396: New York City | K9396: New York | L9396: 10011 | M9396: East | N9396: FUR-CH-10001394 | O9396: Furniture | P9396: Chairs | Q9396: Global Leather Executive Chair | R9396: 631.782
A9397: 9396 | B9397: CA-2015-125997 | C9397: 42267 | D9397: 42270 | E9397: First Class | F9397: MW-18220 | G9397: Mitch Webber | H9397: Consumer | I9397: United States | J9397: New York City | K9397: New York | L9397: 10011 | M9397: East | N9397: FUR-BO-10002213 | O9397: Furniture | P9397: Bookcases | Q9397: DMI Eclipse Executive Suite Bookcases | R9397: 801.568
A9398: 9397 | B9398: CA-2015-125997 | C9398: 42267 | D9398: 42270 | E9398: First Class | F9398: MW-18220 | G9398: Mitch Webber | H9398: Consumer | I9398: United States | J9398: New York City | K9398: New York | L9398: 10011 | M9398: East | N9398: OFF-LA-10002762 | O9398: Office Supplies | P9398: Labels | Q9398: Avery 485 | R9398: 75.18
A9399: 9398 | B9399: CA-2015-125997 | C9399: 42267 | D9399: 42270 | E9399: First Class | F9399: MW-18220 | G9399: Mitch Webber | H9399: Consumer | I9399: United States | J9399: New York City | K9399: New York | L9399: 10011 | M9399: East | N9399: OFF-AP-10003842 | O9399: Office Supplies | P9399: Appliances | Q9399: Euro-Pro Shark Turbo Vacuum | R9399: 30.98
A9400: 9399 | B9400: CA-2015-125997 | C9400: 42267 | D9400: 42270 | E9400: First Class | F9400: MW-18220 | G9400: Mitch Webber | H9400: Consumer | I9400: United States | J9400: New York City | K9400: New York | L9400: 10011 | M9400: East | N9400: TEC-PH-10003072 | O9400: Technology | P9400: Phones | Q9400: Panasonic KX-TG9541B DECT 6.0 Digital 2-Line Expandable Cordless Phone With Digital Answering System | R9400: 1349.91
A9401: 9400 | B9401: CA-2017-103128 | C9401: 43050 | D9401: 43054 | E9401: Standard Class | F9401: SC-20845 | G9401: Sung Chung | H9401: Consumer | I9401: United States | J9401: Arlington Heights | K9401: Illinois | L9401: 60004 | M9401: Central | N9401: OFF-AR-10003394 | O9401: Office Supplies | P9401: Art | Q9401: Newell 332 | R9401: 14.112
A9402: 9401 | B9402: CA-2016-167696 | C9402: 42629 | D9402: 42634 | E9402: Standard Class | F9402: BD-11500 | G9402: Bradley Drucker | H9402: Consumer | I9402: United States | J9402: Newport News | K9402: Virginia | L9402: 23602 | M9402: South | N9402: OFF-EN-10001539 | O9402: Office Supplies | P9402: Envelopes | Q9402: Staple envelope | R9402: 31.12
A9403: 9402 | B9403: CA-2015-159814 | C9403: 42179 | D9403: 42183 | E9403: Standard Class | F9403: LP-17080 | G9403: Liz Pelletier | H9403: Consumer | I9403: United States | J9403: Tucson | K9403: Arizona | L9403: 85705 | M9403: West | N9403: FUR-FU-10001731 | O9403: Furniture | P9403: Furnishings | Q9403: Acrylic Self-Standing Desk Frames | R9403: 4.272
... A9742: 9741 | B9742: CA-2018-129294 | C9742: 43175 | D9742: 43180 | E9742: Standard Class | F9742: KD-16615 | G9742: Ken Dana | H9742: Corporate | I9742: United States | J9742: Los Angeles | K9742: California | L9742: 90032 | M9742: West | N9742: OFF-AP-10001154 | O9742: Office Supplies | P9742: Appliances | Q9742: Bionaire Personal Warm Mist Humidifier/Vaporizer | R9742: 140.67
A9743: 9742 | B9743: CA-2016-117086 | C9743: 42682 | D9743: 42686 | E9743: Standard Class | F9743: QJ-19255 | G9743: Quincy Jones | H9743: Corporate | I9743: United States | J9743: Burlington | K9743: Vermont | M9743: East | N9743: FUR-BO-10004834 | O9743: Furniture | P9743: Bookcases | Q9743: Riverside Palais Royal Lawyers Bookcase, Royale Cherry Finish | R9743: 4404.9
A9744: 9743 | B9744: CA-2018-131303 | C9744: 43432 | D9744: 43436 | E9744: Standard Class | F9744: EP-13915 | G9744: Emily Phan | H9744: Consumer | I9744: United States | J9744: San Diego | K9744: California | L9744: 92037 | M9744: West | N9744: OFF-LA-10001074 | O9744: Office Supplies | P9744: Labels | Q9744: Round Specialty Laser Printer Labels | R9744: 62.65
A9745: 9744 | B9745: CA-2017-137127 | C9745: 42902 | D9745: 42908 | E9745: Standard Class | F9745: JJ-15445 | G9745: Jennifer Jackson | H9745: Consumer | I9745: United States | J9745: Newark | K9745: Delaware | L9745: 19711 | M9745: East | N9745: OFF-LA-10001641 | O9745: Office Supplies | P9745: Labels | Q9745: Avery 518 | R9745: 9.45
A9746: 9745 | B9746: CA-2018-141782 | C9746: 43121 | D9746: 43125 | E9746: Standard Class | F9746: BE-11410 | G9746: Bobby Elias | H9746: Consumer | I9746: United States | J9746: Aurora | K9746: Illinois | L9746: 60505 | M9746: Central | N9746: OFF-EN-10002230 | O9746: Office Supplies | P9746: Envelopes | Q9746: Airmail Envelopes | R9746: 268.576
A9747: 9746 | B9747: CA-2018-137505 | C9747: 43428 | D9747: 43428 | E9747: Same Day | F9747: BP-11290 | G9747: Beth Paige | H9747: Consumer | I9747: United States | J9747: Los Angeles | K9747: California | L9747: 90008 | M9747: West | N9747: FUR-TA-10000617 | O9747: Furniture | P9747: Tables | Q9747: Hon Practical Foundations 30 x 60 Training Table, Light Gray/Charcoal | R9747: 364.08
A9748: 9747 | B9748: CA-2018-137505 | C9748: 43428 | D9748: 43428 | E9748: Same Day | F9748: BP-11290 | G9748: Beth Paige | H9748: Consumer | I9748: United States | J9748: Los Angeles | K9748: California | L9748: 90008 | M9748: West | N9748: FUR-TA-10001676 | O9748: Furniture | P9748: Tables | Q9748: Hon 61000 Series Interactive Training Tables | R9748: 71.088
A9749: 9748 | B9749: US-2015-140914 | C9749: 42319 | D9749: 42323 | E9749: Standard Class | F9749: BH-11710 | G9749: Brosina Hoffman | H9749: Consumer | I9749: United States | J9749: Chicago | K9749: Illinois | L9749: 60653 | M9749: Central | N9749: FUR-FU-10000175 | O9749: Furniture | P9749: Furnishings | Q9749: DAX Wood Document Frame. | R9749: 10.984
A9750: 9749 | B9750: US-2015-140914 | C9750: 42319 | D9750: 42323 | E9750: Standard Class | F9750: BH-11710 | G9750: Brosina Hoffman | H9750: Consumer | I9750: United States | J9750: Chicago | K9750: Illinois | L9750: 60653 | M9750: Central | N9750: FUR-CH-10003379 | O9750: Furniture | P9750: Chairs | Q9750: Global Commerce Series High-Back Swivel/Tilt Chairs | R9750: 797.944
A9751: 9750 | B9751: CA-2017-158358 | C9751: 42798 | D9751: 42802 | E9751: Standard Class | F9751: EM-13810 | G9751: Eleni McCrary | H9751: Corporate | I9751: United States | J9751: Dover | K9751: New Hampshire | L9751: 3820 | M9751: East | N9751: TEC-AC-10002567 | O9751: Technology | P9751: Accessories | Q9751: Logitech G602 Wireless Gaming Mouse | R9751: 159.98
A9752: 9751 | B9752: CA-2017-113390 | C9752: 43019 | D9752: 43023 | E9752: Standard Class | F9752: EP-13915 | G9752: Emily Phan | H9752: Consumer | I9752: United States | J9752: Chicago | K9752: Illinois | L9752: 60610 | M9752: Central | N9752: OFF-AR-10003183 | O9752: Office Supplies | P9752: Art | Q9752: Avery Fluorescent Highlighter Four-Color Set | R9752: 5.344
A9753: 9752 | B9753: CA-2017-113390 | C9753: 43019 | D9753: 43023 | E9753: Standard Class | F9753: EP-13915 | G9753: Emily Phan | H9753: Consumer | I9753: United States | J9753: Chicago | K9753: Illinois | L9753: 60610 | M9753: Central | N9753: OFF-AR-10001446 | O9753: Office Supplies | P9753: Art | Q9753: Newell 309 | R9753: 27.72
...

Sheet PivotTables
A3: Row Labels | B3: Sum of Sales | C3: Region (Clean) | D3: Sum of Sales | G3: Row Labels | H3: Count of Customer ID | I3: Category (Clean) | J3: Percentage of customers | L3: Sum of Sales | M3: Column Labels | Y3: Row Labels | Z3: Sum of Sales | AB3: Category | AC3: Sales | AE3: Row Labels | AF3: Count of Customer ID
A4: Central | B4: 492646.91 | C4: =OFFSET($A$4, ROW()-ROW($C$4),0) -> Central | D4: =OFFSET($B$4, ROW()-ROW($D$4),0) -> 492646.91 | G4: Furniture | H4: 0.21204082 | I4: =OFFSET($G$4, ROW()-ROW($I$4),0) -> Furniture | J4: =OFFSET($H$4, ROW()-ROW($J$4),0) -> 0.21204082 | L4: Row Labels | M4: 2015 | N4: 2016 | O4: 2017 | P4: 2018 | Q4: Grand Total | R4: Month | S4: 2015 | T4: 2016 | U4: 2017 | V4: 2018 | W4: Total (Monthly) | Y4: Furniture | Z4: 728658.58 | AB4: =OFFSET($Y$4, ROW()-ROW($AB$4),0) -> Furniture | AC4: =OFFSET($Z$4, ROW()-ROW($AC$4),0) -> 728658.58 | AE4: Central | AF4: 2277 | AG4: =OFFSET($AE$4, ROW()-ROW($AG$4),0) -> Central | AH4: =OFFSET($AF$4, ROW()-ROW($AH$4),0) -> 2277 | AJ4: Row Labels | AK4: Sum of Sales | AL4: Segment | AM4: Sales | AO4: Row Labels | AP4: Count of Customer ID | AU4: Row Labels | AV4: Sum of Sales | BA4: Count of Customer ID | BB4: Column Labels | BM4: Count of Customer ID | BN4: Column Labels | BS4: Row Labels | BT4: Sum of Sales | BW4: Row Labels | BX4: Sum of Sales | CA4: Row Labels | CB4: Sum of Sales
A5: East | B5: 669518.73 | C5: =OFFSET($A$4, ROW()-ROW($C$4),0) -> East | D5: =OFFSET($B$4, ROW()-ROW($D$4),0) -> 669518.73 | G5: Office Supplies | H5: 0.60295918 | I5: =OFFSET($G$4, ROW()-ROW($I$4),0) -> Office Supplies | J5: =OFFSET($H$4, ROW()-ROW($J$4),0) -> 0.60295918 | L5: Jan | M5: 14205.707 | N5: 18066.958 | O5: 18542.491 | P5: 43476.474 | Q5: 94291.63 | R5: =OFFSET($L$5, ROW()-ROW($R$5),0) -> Jan | S5: =OFFSET($M$5, ROW()-ROW($S$5),0) -> 14205.707 | T5: =OFFSET($N$5, ROW()-ROW($T$5),0) -> 18066.958 | U5: =OFFSET($O$5, ROW()-ROW($U$5),0) -> 18542.491 | V5: =OFFSET($P$5, ROW()-ROW($V$5),0) -> 43476.474 | W5: =OFFSET($Q$5, ROW()-ROW($W$5),0) -> 94291.63 | Y5: Office Supplies | Z5: 705422.33 | AB5: =OFFSET($Y$4, ROW()-ROW($AB$4),0) -> Office Supplies | AC5: =OFFSET($Z$4, ROW()-ROW($AC$4),0) -> 705422.33 | AE5: East | AF5: 2785 | AG5: =OFFSET($AE$4, ROW()-ROW($AG$4),0) -> East | AH5: =OFFSET($AF$4, ROW()-ROW($AH$4),0) -> 2785 | AJ5: Consumer | AK5: 0.50764619 | AL5: =OFFSET($AJ$5, ROW()-ROW($AL$5),0) -> Consumer | AM5: =OFFSET($AK$5, ROW()-ROW($AM$5),0) -> 0.50764619 | AO5: Furniture | AP5: 2078 | AU5: Phones | AV5: 327782.45 | AX5: =OFFSET($AU$5, ROW()-ROW($AX$5),0) -> Phones | AY5: =OFFSET($AV$5, ROW()-ROW($AY$5),0) -> 327782.45 | BA5: Row Labels | BB5: Furniture | BC5: Office Supplies | BD5: Technology | BE5: Grand Total | BH5: =OFFSET($BB$5, ROW()-ROW($BH$5),0) -> Furniture | BI5: =OFFSET($BC$5, ROW()-ROW($BI$5),0) -> Office Supplies | BJ5: =OFFSET($BD$5, ROW()-ROW($BJ$5),0) -> Technology | BK5: =OFFSET($BE$5, ROW()-ROW($BK$5),0) -> Grand Total | BM5: Row Labels | BN5: Consumer | BO5: Corporate | BP5: Home Office | BQ5: Grand Total | BS5: 2015 | BT5: 479856.21 | BW5: 2015 | BX5: 479856.21 | CA5: Central | CB5: 0.21783723
A6: South | B6: 389151.46 | C6: =OFFSET($A$4, ROW()-ROW($C$4),0) -> South | D6: =OFFSET($B$4, ROW()-ROW($D$4),0) -> 389151.46 | G6: Technology | H6: 0.185 | I6: =OFFSET($G$4, ROW()-ROW($I$4),0) -> Technology | J6: =OFFSET($H$4, ROW()-ROW($J$4),0) -> 0.185 | L6: Feb | M6: 4519.892 | N6: 11951.411 | O6: 22978.815 | P6: 19920.997 | Q6: 59371.115 | R6: =OFFSET($L$5, ROW()-ROW($R$5),0) -> Feb | S6: =OFFSET($M$5, ROW()-ROW($S$5),0) -> 4519.892 | T6: =OFFSET($N$5, ROW()-ROW($T$5),0) -> 11951.411 | U6: =OFFSET($O$5, ROW()-ROW($U$5),0) -> 22978.815 | V6: =OFFSET($P$5, ROW()-ROW($V$5),0) -> 19920.997 | W6: =OFFSET($Q$5, ROW()-ROW($W$5),0) -> 59371.115 | Y6: Technology | Z6: 827455.87 | AB6: =OFFSET($Y$4, ROW()-ROW($AB$4),0) -> Technology | AC6: =OFFSET($Z$4, ROW()-ROW($AC$4),0) -> 827455.87 | AE6: South | AF6: 1598 | AG6: =OFFSET($AE$4, ROW()-ROW($AG$4),0) -> South | AH6: =OFFSET($AF$4, ROW()-ROW($AH$4),0) -> 1598 | AJ6: Corporate | AK6: 0.30443638 | AL6: =OFFSET($AJ$5, ROW()-ROW($AL$5),0) -> Corporate | AM6: =OFFSET($AK$5, ROW()-ROW($AM$5),0) -> 0.30443638 | AO6: Office Supplies | AP6: 5909 | AU6: Chairs | AV6: 322822.73 | AX6: =OFFSET($AU$5, ROW()-ROW($AX$5),0) -> Chairs | AY6: =OFFSET($AV$5, ROW()-ROW($AY$5),0) -> 322822.73 | BA6: Consumer | BB6: 1093 | BC6: 3072 | BD6: 936 | BE6: 5101 | BG6: =OFFSET($BA$6, ROW()-ROW($BG$6),0) -> Consumer | BH6: =OFFSET($BB$6, ROW()-ROW($BH$6),0) -> 1093 | BI6: =OFFSET($BC$6, ROW()-ROW($BI$6),0) -> 3072 | BJ6: =OFFSET($BD$6, ROW()-ROW($BJ$6),0) -> 936 | BK6: =OFFSET($BE$6, ROW()-ROW($BK$6),0) -> 5101 | BM6: Central | BN6: 1188 | BO6: 661 | BP6: 428 | BQ6: 2277 | BS6: 2016 | BT6: 459436.01 | BW6: 2016 | BX6: 459436.01 | CA6: East | CB6: 0.29604591
A7: West | B7: 710219.68 | C7: =OFFSET($A$4, ROW()-ROW($C$4),0) -> West | D7: =OFFSET($B$4, ROW()-ROW($D$4),0) -> 710219.68 | I7: =OFFSET($G$4, ROW()-ROW($I$4),0) -> 0 | J7: =OFFSET($H$4, ROW()-ROW($J$4),0) -> 0 | L7: Mar | M7: 55205.797 | N7: 32339.318 | O7: 51165.059 | P7: 58863.413 | Q7: 197573.59 | R7: =OFFSET($L$5, ROW()-ROW($R$5),0) -> Mar | S7: =OFFSET($M$5, ROW()-ROW($S$5),0) -> 55205.797 | T7: =OFFSET($N$5, ROW()-ROW($T$5),0) -> 32339.318 | U7: =OFFSET($O$5, ROW()-ROW($U$5),0) -> 51165.059 | V7: =OFFSET($P$5, ROW()-ROW($V$5),0) -> 58863.413 | W7: =OFFSET($Q$5, ROW()-ROW($W$5),0) -> 197573.59 | AB7: =OFFSET($Y$4, ROW()-ROW($AB$4),0) -> 0 | AC7: =OFFSET($Z$4, ROW()-ROW($AC$4),0) -> 0 | AE7: West | AF7: 3140 | AG7: =OFFSET($AE$4, ROW()-ROW($AG$4),0) -> West | AH7: =OFFSET($AF$4, ROW()-ROW($AH$4),0) -> 3140 | AJ7: Home Office | AK7: 0.18791743 | AL7: =OFFSET($AJ$5, ROW()-ROW($AL$5),0) -> Home Office | AM7: =OFFSET($AK$5, ROW()-ROW($AM$5),0) -> 0.18791743 | AO7: Technology | AP7: 1813 | AU7: Storage | AV7: 219343.39 | AX7: =OFFSET($AU$5, ROW()-ROW($AX$5),0) -> Storage | AY7: =OFFSET($AV$5, ROW()-ROW($AY$5),0) -> 219343.39 | BA7: Corporate | BB7: 628 | BC7: 1783 | BD7: 542 | BE7: 2953 | BG7: =OFFSET($BA$6, ROW()-ROW($BG$6),0) -> Corporate | BH7: =OFFSET($BB$6, ROW()-ROW($BH$6),0) -> 628 | BI7: =OFFSET($BC$6, ROW()-ROW($BI$6),0) -> 1783 | BJ7: =OFFSET($BD$6, ROW()-ROW($BJ$6),0) -> 542 | BK7: =OFFSET($BE$6, ROW()-ROW($BK$6),0) -> 2953 | BM7: East | BN7: 1444 | BO7: 850 | BP7: 491 | BQ7: 2785 | BS7: 2017 | BT7: 600192.55 | BW7: 2017 | BX7: 600192.55 | CA7: South | CB7: 0.1720739
A8: Grand Total | B8: 2261536.8 | C8: =OFFSET($A$4, ROW()-ROW($C$4),0) -> Grand Total | D8: =OFFSET($B$4, ROW()-ROW($D$4),0) -> 2261536.8 | L8: Apr | M8: 27906.855 | N8: 34154.468 | O8: 38679.767 | P8: 35541.91 | Q8: 136283 | R8: =OFFSET($L$5, ROW()-ROW($R$5),0) -> Apr | S8: =OFFSET($M$5, ROW()-ROW($S$5),0) -> 27906.855 | T8: =OFFSET($N$5, ROW()-ROW($T$5),0) -> 34154.468 | U8: =OFFSET($O$5, ROW()-ROW($U$5),0) -> 38679.767 | V8: =OFFSET($P$5, ROW()-ROW($V$5),0) -> 35541.91 | W8: =OFFSET($Q$5, ROW()-ROW($W$5),0) -> 136283 | AE8: Grand Total | AF8: 9800 | AG8: =OFFSET($AE$4, ROW()-ROW($AG$4),0) -> Grand Total | AH8: =OFFSET($AF$4, ROW()-ROW($AH$4),0) -> 9800 | AL8: =OFFSET($AJ$5, ROW()-ROW($AL$5),0) -> 0 | AM8: =OFFSET($AK$5, ROW()-ROW($AM$5),0) -> 0 | AO8: Grand Total | AP8: 9800 | AU8: Tables | AV8: 202810.63 | AX8: =OFFSET($AU$5, ROW()-ROW($AX$5),0) -> Tables | AY8: =OFFSET($AV$5, ROW()-ROW($AY$5),0) -> 202810.63 | BA8: Home Office | BB8: 357 | BC8: 1054 | BD8: 335 | BE8: 1746 | BG8: =OFFSET($BA$6, ROW()-ROW($BG$6),0) -> Home Office | BH8: =OFFSET($BB$6, ROW()-ROW($BH$6),0) -> 357 | BI8: =OFFSET($BC$6, ROW()-ROW($BI$6),0) -> 1054 | BJ8: =OFFSET($BD$6, ROW()-ROW($BJ$6),0) -> 335 | BK8: =OFFSET($BE$6, ROW()-ROW($BK$6),0) -> 1746 | BM8: South | BN8: 831 | BO8: 500 | BP8: 267 | BQ8: 1598 | BS8: 2018 | BT8: 722052.02 | BW8: 2018 | BX8: 722052.02 | CA8: West | CB8: 0.31404295
L9: May | M9: 23644.303 | N9: 29959.53 | O9: 56656.908 | P9: 43825.982 | Q9: 154086.72 | R9: =OFFSET($L$5, ROW()-ROW($R$5),0) -> May | S9: =OFFSET($M$5, ROW()-ROW($S$5),0) -> 23644.303 | T9: =OFFSET($N$5, ROW()-ROW($T$5),0) -> 29959.53 | U9: =OFFSET($O$5, ROW()-ROW($U$5),0) -> 56656.908 | V9: =OFFSET($P$5, ROW()-ROW($V$5),0) -> 43825.982 | W9: =OFFSET($Q$5, ROW()-ROW($W$5),0) -> 154086.72 | AU9: Binders | AV9: 200028.79 | AX9: =OFFSET($AU$5, ROW()-ROW($AX$5),0) -> Binders | AY9: =OFFSET($AV$5, ROW()-ROW($AY$5),0) -> 200028.79 | BA9: Grand Total | BB9: 2078 | BC9: 5909 | BD9: 1813 | BE9: 9800 | BG9: =OFFSET($BA$6, ROW()-ROW($BG$6),0) -> Grand Total | BH9: =OFFSET($BB$6, ROW()-ROW($BH$6),0) -> 2078 | BI9: =OFFSET($BC$6, ROW()-ROW($BI$6),0) -> 5909 | BJ9: =OFFSET($BD$6, ROW()-ROW($BJ$6),0) -> 1813 | BK9: =OFFSET($BE$6, ROW()-ROW($BK$6),0) -> 9800 | BM9: West | BN9: 1638 | BO9: 942 | BP9: 560 | BQ9: 3140 | BS9: Grand Total | BT9: 2261536.8 | BW9: Grand Total | BX9: 2261536.8 | CA9: Grand Total | CB9: 1
L10: Jun | M10: 34322.936 | N10: 23599.374 | O10: 39724.486 | P10: 48190.728 | Q10: 145837.52 | R10: =OFFSET($L$5, ROW()-ROW($R$5),0) -> Jun | S10: =OFFSET($M$5, ROW()-ROW($S$5),0) -> 34322.936 | T10: =OFFSET($N$5, ROW()-ROW($T$5),0) -> 23599.374 | U10: =OFFSET($O$5, ROW()-ROW($U$5),0) -> 39724.486 | V10: =OFFSET($P$5, ROW()-ROW($V$5),0) -> 48190.728 | W10: =OFFSET($Q$5, ROW()-ROW($W$5),0) -> 145837.52 | AU10: Machines | AV10: 189238.63 | AX10: =OFFSET($AU$5, ROW()-ROW($AX$5),0) -> Machines | AY10: =OFFSET($AV$5, ROW()-ROW($AY$5),0) -> 189238.63 | BM10: Grand Total | BN10: 5101 | BO10: 2953 | BP10: 1746 | BQ10: 9800
L11: Jul | M11: 33781.543 | N11: 28608.259 | O11: 38320.783 | P11: 44825.104 | Q11: 145535.69 | R11: =OFFSET($L$5, ROW()-ROW($R$5),0) -> Jul | S11: =OFFSET($M$5, ROW()-ROW($S$5),0) -> 33781.543 | T11: =OFFSET($N$5, ROW()-ROW($T$5),0) -> 28608.259 | U11: =OFFSET($O$5, ROW()-ROW($U$5),0) -> 38320.783 | V11: =OFFSET($P$5, ROW()-ROW($V$5),0) -> 44825.104 | W11: =OFFSET($Q$5, ROW()-ROW($W$5),0) -> 145535.69 | AU11: Accessories | AV11: 164186.7 | AX11: =OFFSET($AU$5, ROW()-ROW($AX$5),0) -> Accessories | AY11: =OFFSET($AV$5, ROW()-ROW($AY$5),0) -> 164186.7
L12: Aug | M12: 27117.536 | N12: 36818.342 | O12: 30542.2 | P12: 62837.848 | Q12: 157315.93 | R12: =OFFSET($L$5, ROW()-ROW($R$5),0) -> Aug | S12: =OFFSET($M$5, ROW()-ROW($S$5),0) -> 27117.536 | T12: =OFFSET($N$5, ROW()-ROW($T$5),0) -> 36818.342 | U12: =OFFSET($O$5, ROW()-ROW($U$5),0) -> 30542.2 | V12: =OFFSET($P$5, ROW()-ROW($V$5),0) -> 62837.848 | W12: =OFFSET($Q$5, ROW()-ROW($W$5),0) -> 157315.93 | AE12: Row Labels | AF12: Count of Customer ID | AU12: Copiers | AV12: 146248.09 | AX12: =OFFSET($AU$5, ROW()-ROW($AX$5),0) -> Copiers | AY12: =OFFSET($AV$5, ROW()-ROW($AY$5),0) -> 146248.09
L13: Sep | M13: 81623.527 | N13: 63133.606 | O13: 69193.391 | P13: 86152.888 | Q13: 300103.41 | R13: =OFFSET($L$5, ROW()-ROW($R$5),0) -> Sep | S13: =OFFSET($M$5, ROW()-ROW($S$5),0) -> 81623.527 | T13: =OFFSET($N$5, ROW()-ROW($T$5),0) -> 63133.606 | U13: =OFFSET($O$5, ROW()-ROW($U$5),0) -> 69193.391 | V13: =OFFSET($P$5, ROW()-ROW($V$5),0) -> 86152.888 | W13: =OFFSET($Q$5, ROW()-ROW($W$5),0) -> 300103.41 | AE13: Central | AF13: 2277 | AU13: Bookcases | AV13: 113813.2 | AX13: =OFFSET($AU$5, ROW()-ROW($AX$5),0) -> Bookcases | AY13: =OFFSET($AV$5, ROW()-ROW($AY$5),0) -> 113813.2
L14: Oct | M14: 31453.393 | N14: 31011.738 | O14: 59583.033 | P14: 77448.131 | Q14: 199496.29 | R14: =OFFSET($L$5, ROW()-ROW($R$5),0) -> Oct | S14: =OFFSET($M$5, ROW()-ROW($S$5),0) -> 31453.393 | T14: =OFFSET($N$5, ROW()-ROW($T$5),0) -> 31011.738 | U14: =OFFSET($O$5, ROW()-ROW($U$5),0) -> 59583.033 | V14: =OFFSET($P$5, ROW()-ROW($V$5),0) -> 77448.131 | W14: =OFFSET($Q$5, ROW()-ROW($W$5),0) -> 199496.29 | AE14: East | AF14: 2785 | AU14: Appliances | AV14: 104618.4 | AX14: =OFFSET($AU$5, ROW()-ROW($AX$5),0) -> Appliances | AY14: =OFFSET($AV$5, ROW()-ROW($AY$5),0) -> 104618.4
L15: Nov | M15: 77907.661 | N15: 75249.4 | O15: 79066.496 | P15: 117938.16 | Q15: 350161.71 | R15: =OFFSET($L$5, ROW()-ROW($R$5),0) -> Nov | S15: =OFFSET($M$5, ROW()-ROW($S$5),0) -> 77907.661 | T15: =OFFSET($N$5, ROW()-ROW($T$5),0) -> 75249.4 | U15: =OFFSET($O$5, ROW()-ROW($U$5),0) -> 79066.496 | V15: =OFFSET($P$5, ROW()-ROW($V$5),0) -> 117938.16 | W15: =OFFSET($Q$5, ROW()-ROW($W$5),0) -> 350161.71 | AE15: South | AF15: 1598 | AG15: =GETPIVOTDATA("Customer ID",$AE$3)/GETPIVOTDATA("Customer ID",$AE$12) -> 1 | AU15: Furnishings | AV15: 89212.018 | AX15: =OFFSET($AU$5, ROW()-ROW($AX$5),0) -> Furnishings | AY15: =OFFSET($AV$5, ROW()-ROW($AY$5),0) -> 89212.018
L16: Dec | M16: 68167.058 | N16: 74543.601 | O16: 95739.121 | P16: 83030.389 | Q16: 321480.17 | R16: =OFFSET($L$5, ROW()-ROW($R$5),0) -> Dec | S16: =OFFSET($M$5, ROW()-ROW($S$5),0) -> 68167.058 | T16: =OFFSET($N$5, ROW()-ROW($T$5),0) -> 74543.601 | U16: =OFFSET($O$5, ROW()-ROW($U$5),0) -> 95739.121 | V16: =OFFSET($P$5, ROW()-ROW($V$5),0) -> 83030.389 | W16: =OFFSET($Q$5, ROW()-ROW($W$5),0) -> 321480.17 | AE16: West | AF16: 3140 | AU16: Paper | AV16: 76828.304 | AX16: =OFFSET($AU$5, ROW()-ROW($AX$5),0) -> Paper | AY16: =OFFSET($AV$5, ROW()-ROW($AY$5),0) -> 76828.304
G17: Row Labels | H17: Sum of Sales | L17: Grand Total | M17: 479856.21 | N17: 459436.01 | O17: 600192.55 | P17: 722052.02 | Q17: 2261536.8 | R17: =OFFSET($L$5, ROW()-ROW($R$5),0) -> Grand Total | S17: =OFFSET($M$5, ROW()-ROW($S$5),0) -> 479856.21 | T17: =OFFSET($N$5, ROW()-ROW($T$5),0) -> 459436.01 | U17: =OFFSET($O$5, ROW()-ROW($U$5),0) -> 600192.55 | V17: =OFFSET($P$5, ROW()-ROW($V$5),0) -> 722052.02 | W17: =OFFSET($Q$5, ROW()-ROW($W$5),0) -> 2261536.8 | AE17: Grand Total | AF17: 9800 | AU17: Supplies | AV17: 46420.308 | AX17: =OFFSET($AU$5, ROW()-ROW($AX$5),0) -> Supplies | AY17: =OFFSET($AV$5, ROW()-ROW($AY$5),0) -> 46420.308
G18: Central | H18: 492646.91 | AU18: Art | AV18: 26705.41 | AX18: =OFFSET($AU$5, ROW()-ROW($AX$5),0) -> Art | AY18: =OFFSET($AV$5, ROW()-ROW($AY$5),0) -> 26705.41
G19: East | H19: 669518.73 | S19: =GETPIVOTDATA("Sales",$L$3,"Years (Order Date)",2015) -> 479856.21 | AU19: Envelopes | AV19: 16128.046 | AX19: =OFFSET($AU$5, ROW()-ROW($AX$5),0) -> Envelopes | AY19: =OFFSET($AV$5, ROW()-ROW($AY$5),0) -> 16128.046
G20: South | H20: 389151.46 | S20: =GETPIVOTDATA("Sales",$L$3,"Years (Order Date)",2016) -> 459436.01 | AU20: Labels | AV20: 12347.726 | AX20: =OFFSET($AU$5, ROW()-ROW($AX$5),0) -> Labels | AY20: =OFFSET($AV$5, ROW()-ROW($AY$5),0) -> 12347.726
G21: West | H21: 710219.68 | AU21: Fasteners | AV21: 3001.96 | AX21: =OFFSET($AU$5, ROW()-ROW($AX$5),0) -> Fasteners | AY21: =OFFSET($AV$5, ROW()-ROW($AY$5),0) -> 3001.96
G22: Grand Total | H22: 2261536.8 | Y22: Sum of Sales | Z22: Column Labels | AU22: Grand Total | AV22: 2261536.8 | AX22: =OFFSET($AU$5, ROW()-ROW($AX$5),0) -> Grand Total | AY22: =OFFSET($AV$5, ROW()-ROW($AY$5),0) -> 2261536.8
Y23: Row Labels | Z23: Furniture | AA23: Office Supplies | AB23: Technology
Y24: Accessories | AB24: 164186.7
Y25: Appliances | AA25: 104618.4
Y26: Art | AA26: 26705.41
Y27: Binders | AA27: 200028.79
Y28: Bookcases | Z28: 113813.2
Y29: Chairs | Z29: 322822.73
Y30: Copiers | AB30: 146248.09
Y31: Envelopes | AA31: 16128.046
Y32: Fasteners | AA32: 3001.96
G33: Row Labels | H33: Sum of Sales | Y33: Furnishings | Z33: 89212.018
G34: Central | H34: 492646.91 | I34: =GETPIVOTDATA("Sales",$G$17)/GETPIVOTDATA("Sales",$G$33) -> 1 | Y34: Labels | AA34: 12347.726
G35: East | H35: 669518.73 | Y35: Machines | AB35: 189238.63
G36: South | H36: 389151.46 | Y36: Paper | AA36: 76828.304
G37: West | H37: 710219.68 | Y37: Phones | AB37: 327782.45
G38: Grand Total | H38: 2261536.8 | Y38: Storage | AA38: 219343.39
Y39: Supplies | AA39: 46420.308
Y40: Tables | Z40: 202810.63

Sheet Dashboard
S2: Total Sales | T2: Avg yearly sales | V2: Sales by region | W2: No. of customers | Y2: Customers by region
S3: =GETPIVOTDATA("Sales",PivotTables!$A$3) -> 2261536.8 | T3: =AVERAGE(GETPIVOTDATA("Sales",PivotTables!$BS$4,"Years (Order Date)",2015),GETPIVOTDATA("Sales",PivotTables!$BS$4,"Years (Order Date)",2016),GETPIVOTDATA("Sales",PivotTables!$BS$4,"Years (Order Date)",2017),GETPIVOTDATA("Sales",PivotTables!$BS$4,"Years (Order Date)",2018)) -> 565384.2 | V3: =PivotTables!I34 -> 1 | W3: =GETPIVOTDATA("Customer ID",PivotTables!$BA$4) -> 9800 | Y3: =PivotTables!AG15 -> 1
